{"type":"FeatureCollection","features":[{"type":"Feature","properties":{"landcover":1,"label":"forest"},"geometry":{"coordinates":[149.28991688140155,-35.74157563051502],"type":"Point"}},{"type":"Feature","properties":{"landcover":1,"label":"forest"},"geometry":{"coordinates":[149.2799573652366,-35.93928029064062],"type":"Point"}},{"type":"Feature","properties":{"landcover":1,"label":"forest"},"geometry":{"coordinates":[148.93888299174193,-35.79426316974096],"type":"Point"}},{"type":"Feature","properties":{"landcover":2,"label":"crop"},"geometry":{"coordinates":[148.83885159621724,-35.98751884107378],"type":"Point"}},{"type":"Feature","properties":{"landcover":2,"label":"crop"},"geometry":{"coordinates":[149.2514515683875,-35.9304513494009],"type":"Point"}},{"type":"Feature","properties":{"landcover":3,"label":"water"},"geometry":{"coordinates":[149.10642499131973,-35.288443471180905],"type":"Point"}},{"type":"Feature","properties":{"landcover":3,"label":"water"},"geometry":{"coordinates":[149.0782991719371,-35.29883836102311],"type":"Point"}},{"type":"Feature","properties":{"landcover":4,"label":"urban"},"geometry":{"coordinates":[149.06693183755306,-35.41632484189991],"type":"Point"}},{"type":"Feature","properties":{"landcover":4,"label":"urban"},"geometry":{"coordinates":[149.08439079212087,-35.399809142606436],"type":"Point"}}]}